{
    "appKeys": {
        "KEY_HOUR_DIAL": 0,
        "KEY_PTOLMAIC": 0
    },
    "capabilities": [
        "configurable"
    ],
    "companyName": "kristof.willen@gmail.com",
    "longName": "Copernicus was wrong",
    "projectType": "native",
    "resources": {
        "media": [
            {
                "file": "images/iss.png",
                "name": "IMAGE_ISS",
                "type": "png"
            },
            {
                "file": "images/moon_color.png",
                "name": "IMAGE_MOON_COLOR",
                "type": "png"
            },
            {
                "file": "images/sun_color.png",
                "name": "IMAGE_SUN_COLOR",
                "type": "png"
            },
            {
                "file": "images/ufo_color.png",
                "name": "IMAGE_UFO_COLOR",
                "type": "png"
            },
            {
                "file": "images/stars_color.png",
                "name": "IMAGE_STARS_COLOR",
                "type": "png"
            },
            {
                "file": "images/earth_color.png",
                "name": "IMAGE_EARTH_COLOR",
                "type": "png"
            },
            {
                "file": "images/stars.png",
                "name": "IMAGE_STARS_BACKGROUND",
                "type": "png"
            },
            {
                "file": "images/ufo.png",
                "name": "IMAGE_UFO_ICON",
                "type": "png"
            },
            {
                "file": "images/moonicon.png",
                "menuIcon": true,
                "name": "IMAGE_MOON_SMALL_ICON",
                "type": "png"
            },
            {
                "file": "images/sunicon.png",
                "name": "IMAGE_SUN_SMALL_ICON",
                "type": "png"
            },
            {
                "file": "images/earth.png",
                "name": "IMAGE_EARTH_ICON",
                "type": "png"
            },
            {
                "file": "images/azimuth.png",
                "name": "IMAGE_AZIMUTH_BACKGROUND",
                "type": "png"
            }
        ]
    },
    "sdkVersion": "3",
    "shortName": "Copernicus was wrong",
    "targetPlatforms": [
        "aplite",
        "basalt"
    ],
    "uuid": "7739c113-8af4-4e50-8bad-a6dc58f139c1",
    "versionLabel": "2.0",
    "watchapp": {
        "watchface": true
    }
}
